setup.cfg
setup.py
featurex/__init__.py
featurex/core.py
featurex/export.py
featurex/lazy.py
featurex/version.py
featurex.egg-info/PKG-INFO
featurex.egg-info/SOURCES.txt
featurex.egg-info/dependency_links.txt
featurex.egg-info/pbr.json
featurex.egg-info/requires.txt
featurex.egg-info/top_level.txt
featurex/datasets/__init__.py
featurex/datasets/text.py
featurex/datasets/utils.py
featurex/external/__init__.py
featurex/external/pySaliencyMap.py
featurex/external/pySaliencyMapDefs.py
featurex/extractors/__init__.py
featurex/extractors/api.py
featurex/extractors/audio.py
featurex/extractors/google.py
featurex/extractors/image.py
featurex/extractors/text.py
featurex/extractors/video.py
featurex/stimuli/__init__.py
featurex/stimuli/audio.py
featurex/stimuli/image.py
featurex/stimuli/text.py
featurex/stimuli/video.py
featurex/support/__init__.py
featurex/support/decorators.py
featurex/support/download.py
featurex/support/exceptions.py
featurex/tests/__init__.py
featurex/tests/test_core.py
featurex/tests/test_datasets.py
featurex/tests/test_extractors.py
featurex/tests/test_google_extractors.py
featurex/tests/test_io.py
featurex/tests/test_stims.py
featurex/tests/utils.py
featurex/tests/data/audio
featurex/tests/data/text
featurex/tests/data/video
featurex/tests/data/audio/barber.wav
featurex/tests/data/audio/barber_edited.wav
featurex/tests/data/image/apple.jpg
featurex/tests/data/image/obama.jpg
featurex/tests/data/payloads/google_vision_api_face_payload.json
featurex/tests/data/text/complex_stim_no_header.txt
featurex/tests/data/text/complex_stim_with_header.txt
featurex/tests/data/text/sample_text.txt
featurex/tests/data/text/scandal.txt
featurex/tests/data/text/test_lexical_dictionary.txt
featurex/tests/data/text/wonderful.srt
featurex/tests/data/text/wonderful.txt
featurex/tests/data/text/wonderful_edited.srt
featurex/tests/data/video/small.mp4