Metadata-Version: 1.1
Name: featurex
Version: 0.0.1
Summary: Multimodal feature extraction in Python
Home-page: http://github.com/tyarkoni/featurex
Author: Tal Yarkoni
Author-email: tyarkoni@gmail.com
License: MIT
Download-URL: https://github.com/tyarkoni/featurex/archive/0.0.1.tar.gz
Platform: UNKNOWN
